<Alloy>
    <ScrollView id="index" class="menuBar">
        <View class="menuItem" onClick="onChangeReport" formFactor="handheld">
            <ImageView class="menuIcon"/>
            <Label class="menuTitle" id="reports"/>
        </View>
        <View class="menuSeparator"/>
        <View class="menuItem" onClick="onChangeMetric">
            <ImageView class="menuIcon"/>
            <Label class="menuTitle" id="metric"/>
        </View>
        <View class="menuSeparator"/>
        <View class="menuItem" onClick="onChangeDate">
            <ImageView class="menuIcon"/>
            <Label class="menuTitle" id="date"/>
        </View>
        <View class="menuSeparator"/>
        <View class="menuItem" onClick="onFlatten">
            <ImageView class="menuIcon"/>
            <Label class="menuTitle" id="flatten"/>
        </View>
    </ScrollView>
</Alloy>